fzf/__init__.py
fzf/options.py
fzf/process.py
krfzf_py-0.0.6.dist-info/LICENSE
krfzf_py-0.0.6.dist-info/METADATA
krfzf_py-0.0.6.dist-info/WHEEL
krfzf_py-0.0.6.dist-info/RECORD
