Metadata-Version: 2.1
Name: krfzf-py
Version: 0.0.6
Summary: Fzf.py - A Pythonic Fzf Wrapper
License: GPTv3
Author: justfoolingaround
Author-email: kr.justfoolingaround@gmail.com
Requires-Python: >=3.9,<4.0
Classifier: License :: Other/Proprietary License
Classifier: Programming Language :: Python :: 3
Classifier: Programming Language :: Python :: 3.9
Classifier: Programming Language :: Python :: 3.10
Classifier: Programming Language :: Python :: 3.11
